<PAMDataset>
  <Metadata>
    <MDI key="DataType">Generic</MDI>
  </Metadata>
  <Metadata domain="Esri">
    <MDI key="PyramidResamplingType">NEAREST</MDI>
  </Metadata>
  <PAMRasterBand band="1">
    <Histograms>
      <HistItem>
        <HistMin>-0.5</HistMin>
        <HistMax>1023.5</HistMax>
        <BucketCount>1024</BucketCount>
        <IncludeOutOfRange>1</IncludeOutOfRange>
        <Approximate>0</Approximate>
        <HistCounts>0|0|0|0|0|0|0|0|0|0|0|0|0|0|0|0|0|0|0|0|0|0|0|0|0|0|0|0|0|0|0|0|0|0|0|0|0|0|0|0|0|0|0|0|0|0|0|0|0|0|0|0|0|0|0|0|0|0|0|0|0|0|0|0|0|0|0|0|0|0|0|0|0|0|0|0|0|0|0|0|0|0|0|0|0|0|0|0|0|0|0|0|0|0|0|0|0|0|0|0|0|0|0|0|0|0|0|0|0|0|0|0|0|0|0|0|0|0|0|0|0|0|0|0|0|0|0|0|0|0|0|0|0|0|0|0|0|0|0|0|0|0|0|0|0|0|0|0|0|0|0|0|0|0|0|0|0|0|0|0|0|0|0|0|0|0|0|0|0|0|0|0|0|0|0|0|0|0|0|0|0|0|0|0|0|0|1|2|3|11|9|10|6|13|20|18|11|25|30|32|37|83|67|96|149|160|237|248|317|359|468|483|499|502|522|579|527|525|578|506|532|576|566|573|610|580|628|630|631|621|672|679|683|786|737|747|847|841|847|898|967|937|992|997|1075|1102|1129|1305|1229|1368|1451|1557|1598|1732|1644|1781|1830|2001|2174|2158|2320|2375|2658|2824|2916|3043|3125|3359|3614|3836|4189|4502|4780|4943|4906|5116|5463|5504|5518|5369|5479|5447|5805|5830|5857|5899|5749|5977|6038|6314|6463|6696|6516|6379|6413|6286|6509|6600|7129|7178|7221|7420|7410|7675|7918|8630|8650|8194|8230|8136|7918|7504|7248|6982|6758|6539|6638|6647|6771|6755|6804|6757|6625|6931|7079|6867|7077|7009|6901|7030|6979|7054|7042|7068|7019|6927|6986|7055|7212|7175|7369|7611|7455|7621|7632|7682|7915|7814|7645|7891|7823|7825|7810|7692|7520|7712|7471|7715|7550|7471|7595|7338|7382|7381|7303|6924|7135|6801|6788|6759|6566|6735|6728|6616|6681|6813|6796|6691|7081|7184|7381|7604|7888|8247|8714|8980|9619|9829|9922|9889|9837|9844|9390|9326|9147|9183|9075|8866|8847|8799|8892|9098|9230|9696|9988|10465|10893|11185|11302|11752|11550|11383|11233|10997|10814|10803|10435|10437|10055|10175|9897|9886|9852|9494|9806|9391|9429|9481|9302|9151|9036|8922|8819|8833|8604|8665|8397|8658|8476|8313|8381|8491|8365|8251|8254|8438|8387|8379|8295|8152|8240|7930|7814|7702|7448|7257|7129|6811|6544|6360|6311|6029|6012|5794|5640|5456|5453|5253|5102|5024|4830|4963|4880|4805|4866|4818|5071|5140|5344|5459|5512|5650|5708|5709|5827|5665|5798|5553|5581|5601|5451|5348|5305|5200|5256|5316|5037|5357|5046|5092|4980|5045|5003|4811|5033|4955|4848|5104|5106|5112|5155|5431|5554|5718|5941|6366|6472|6805|7164|7553|8092|8296|8639|8872|9445|9556|9770|10186|10581|10618|10819|10784|10820|10819|10421|10468|10343|9759|9878|9699|9464|9482|9257|8879|8409|8053|7739|7508|7193|6660|6465|6312|6111|6208|5955|5946|5659|5731|5555|5414|5447|5516|5155|5118|4762|4719|4555|4281|4113|3912|3843|3699|3541|3422|3133|3071|2934|2746|2839|2778|2712|2563|2593|2453|2578|2487|2338|2271|2299|2260|2100|2070|1957|1922|1860|1699|1562|1510|1415|1312|1298|1130|1028|962|965|890|819|753|769|786|664|670|633|633|645|575|532|549|568|602|561|528|526|531|510|495|510|456|476|455|469|473|435|431|356|408|411|393|399|398|415|383|409|406|382|449|433|384|415|380|413|367|389|382|380|377|369|366|343|396|329|304|337|347|337|287|332|320|327|273|327|313|284|314|267|288|293|255|251|274|230|267|240|256|222|237|218|203|213|227|185|195|187|193|181|157|152|147|120|157|124|126|116|128|123|119|131|115|109|105|97|104|102|104|75|87|68|76|83|93|78|69|50|66|48|54|48|47|59|50|49|50|52|56|50|40|46|40|46|44|46|37|46|38|44|48|45|42|46|36|40|38|38|37|30|47|24|27|37|24|31|35|39|21|23|39|29|22|33|33|24|23|22|31|22|30|14|21|17|21|19|15|29|13|18|26|16|15|19|18|22|15|11|17|19|18|15|7|12|15|20|16|18|4|13|17|16|9|12|13|15|13|11|7|9|11|12|9|8|12|8|14|10|11|4|9|12|12|13|13|8|12|11|14|7|11|9|10|11|3|10|6|13|13|10|8|7|7|8|8|7|4|16|8|8|11|8|6|6|12|6|5|8|8|6|5|9|7|9|10|4|7|7|6|9|8|11|3|7|10|7|10|10|4|1|6|3|4|6|3|0|3|0|6|4|9|5|5|9|1|5|7|3|2|1|3|4|5|4|8|6|11|6|5|5|8|4|1|6|4|0|6|8|4|3|1|2|1|1|1|3|8|0|4|2|6|2|1|0|1|4|2|2|4|0|2|1|7|0|1|2|1|2|0|4|1|4|1|2|2|1|1|1|1|1|0|1|0|2|3|2|1|1|1|0|0|0|2|2|2|1|0|0|2|2|0|3|5|0|0|2|3|1|4|3|2|2|2|3|1|1|0|4|0|0|2|1|2|1|0|1|2|2|1|1|2|0|2|1|5|2|3|5|46</HistCounts>
      </HistItem>
    </Histograms>
    <Metadata>
      <MDI key="RepresentationType">ATHEMATIC</MDI>
      <MDI key="STATISTICS_COVARIANCES">9198.179644626043,8520.480746359215,3959.429539735342,-4430.962635072909</MDI>
      <MDI key="STATISTICS_MAXIMUM">1023</MDI>
      <MDI key="STATISTICS_MEAN">423.07226158922</MDI>
      <MDI key="STATISTICS_MINIMUM">186</MDI>
      <MDI key="STATISTICS_SKIPFACTORX">1</MDI>
      <MDI key="STATISTICS_SKIPFACTORY">1</MDI>
      <MDI key="STATISTICS_STDDEV">95.907140738456</MDI>
    </Metadata>
  </PAMRasterBand>
  <PAMRasterBand band="2">
    <Histograms>
      <HistItem>
        <HistMin>-0.5</HistMin>
        <HistMax>1023.5</HistMax>
        <BucketCount>1024</BucketCount>
        <IncludeOutOfRange>1</IncludeOutOfRange>
        <Approximate>0</Approximate>
        <HistCounts>0|0|0|0|0|0|0|0|0|0|0|0|0|0|0|0|0|0|0|0|0|0|0|0|0|0|0|0|0|0|0|0|0|0|0|0|0|0|0|0|0|0|0|0|0|0|0|0|0|0|0|0|0|0|0|0|0|0|0|0|0|0|0|0|0|0|0|0|0|0|0|0|0|0|0|0|0|0|0|0|0|0|0|0|0|0|0|0|0|0|0|0|0|0|0|0|0|0|0|0|0|0|0|0|0|0|0|0|0|0|0|0|0|0|0|0|0|0|0|0|0|0|0|0|0|0|0|0|0|0|0|0|0|0|0|0|0|0|0|0|0|0|0|0|0|0|0|0|0|0|0|0|0|0|0|0|0|0|0|0|0|0|0|0|0|0|0|0|0|0|0|0|0|0|0|0|0|0|0|0|0|0|0|0|0|0|0|1|0|0|0|0|0|0|1|0|1|0|4|1|7|6|6|7|6|10|14|6|8|11|8|19|15|17|15|16|21|19|24|39|59|72|99|160|186|201|228|249|271|325|349|431|505|606|736|787|871|928|886|929|1027|1164|1225|1229|1196|1032|927|936|968|1009|910|946|891|914|996|1012|1086|1090|1126|1121|1126|1174|1171|1166|1263|1287|1338|1303|1368|1448|1445|1532|1492|1436|1517|1432|1470|1499|1588|1588|1653|1627|1671|1871|1903|1964|2032|2210|2200|2179|2173|2232|2313|2445|2505|2578|2705|2611|2784|3047|3222|3483|3663|3854|3719|3705|3669|3518|3500|3613|3488|3169|3257|3177|2925|2896|2881|2903|2870|2836|2857|2896|2896|2981|2837|2804|2975|2914|3072|3134|3079|3085|3248|3173|3158|3155|3258|3170|3457|3321|3367|3363|3511|3574|3586|3570|3470|3544|3675|3649|3688|3674|3917|3818|3870|3831|3715|3792|3845|3828|3983|3894|3849|3931|4088|4073|4124|4028|4084|4148|4039|4206|4139|4070|4285|4183|4051|4318|4097|4357|4277|4207|4277|4388|4552|4523|4621|4469|4702|4626|4737|4786|4856|4866|4824|4978|5032|5116|5053|4809|5152|5047|5197|5003|5134|5180|5222|5200|5235|5287|5136|5218|5225|5098|5255|5310|5092|5310|5380|5312|5241|5269|5364|5293|5443|5441|5372|5342|5277|5312|5523|5341|5519|5415|5469|5434|5486|5482|5600|5669|5511|5464|5590|5438|5483|5507|5616|5582|5511|5742|5625|5622|5758|5737|5800|5857|5872|5963|5854|6010|6003|6010|6273|6551|6674|6931|7196|7381|7496|7498|7775|7875|7904|8056|7862|8236|8112|8267|8487|8385|8432|8424|8707|8578|8832|8940|8965|8164|9289|9050|8992|9154|9139|9070|9024|9055|9086|9149|9145|9240|9439|9425|9433|9751|9937|10317|10467|10821|11218|11370|11583|11780|12025|12122|12260|12318|12355|12335|12892|12517|12969|13203|13173|13362|13427|13400|13829|13764|14196|14209|14379|14602|14365|14132|14489|14579|14771|14705|14605|14548|14636|14470|14319|14640|14199|13905|13936|13865|13369|13124|12824|12534|12136|12031|11704|11195|11094|10685|10293|10192|9989|9352|9370|9450|8900|8712|8637|8600|8452|8514|8307|8042|8030|7771|7745|7159|7603|7454|7549|7386|7416|7138|6904|7139|6867|7042|6595|6653|6444|6276|6214|5986|5972|5882|5605|5492|5299|5148|5131|5115|5093|4864|4978|4959|4630|4553|4662|4625|4415|4224|4212|4205|4056|4081|3986|3873|3901|3781|3741|3536|3555|3352|3225|3149|3190|2929|2933|2898|2746|2716|2598|2432|2294|2255|2248|2137|2003|1952|1848|1812|1879|1650|1648|1591|1517|1443|1512|1282|1362|1290|1238|1245|1083|1103|1051|981|975|992|879|885|865|785|740|748|766|734|700|710|680|632|706|602|630|578|554|489|492|522|483|508|495|435|454|467|461|440|392|465|411|418|442|401|366|375|365|347|372|365|339|349|391|365|342|350|319|324|340|311|322|315|311|313|263|290|288|263|255|257|267|282|265|265|246|234|262|240|221|213|243|235|235|214|240|224|187|208|224|187|201|199|173|219|218|215|226|230|206|218|236|221|198|216|217|214|219|210|185|237|233|226|234|226|205|203|214|208|232|213|227|216|226|224|191|234|204|214|219|225|197|210|212|199|197|232|190|200|194|197|192|195|201|193|170|205|169|175|195|166|199|176|232|194|197|179|168|184|157|148|161|145|161|155|150|161|127|154|156|116|131|129|134|127|117|125|120|112|89|112|98|127|113|93|100|91|76|96|100|76|82|90|102|81|78|81|71|87|78|89|54|72|74|73|83|46|49|57|74|59|57|48|69|70|46|59|69|53|35|38|42|48|36|29|36|37|34|39|30|32|26|42|40|30|34|36|43|27|37|32|19|32|28|24|35|25|22|27|30|22|16|22|23|21|16|22|25|14|26|27|10|26|20|10|19|20|21|19|18|14|17|17|18|23|22|20|20|20|12|18|10|13|15|18|18|22|13|10|21|22|13|12|19|8|14|19|10|14|7|9|12|17|14|17|17|11|9|12|12|11|15|14|18|9|11|16|7|16|14|6|11|10|11|15|18|8|12|5|10|8|9|12|10|11|9|5|12|5|9|6|8|13|15|16|8|8|13|22|10|8|9|9|10|14|8|12|5|13|8|13|12|5|16|11|7|6|5|6|6|7|5|12|11|10|46|1095</HistCounts>
      </HistItem>
    </Histograms>
    <Metadata>
      <MDI key="RepresentationType">ATHEMATIC</MDI>
      <MDI key="STATISTICS_COVARIANCES">8520.480746359215,10012.86671850592,9309.004785173107,1411.599133658543</MDI>
      <MDI key="STATISTICS_MAXIMUM">1023</MDI>
      <MDI key="STATISTICS_MEAN">488.09859943162</MDI>
      <MDI key="STATISTICS_MINIMUM">187</MDI>
      <MDI key="STATISTICS_SKIPFACTORX">1</MDI>
      <MDI key="STATISTICS_SKIPFACTORY">1</MDI>
      <MDI key="STATISTICS_STDDEV">100.06431291178</MDI>
    </Metadata>
  </PAMRasterBand>
  <PAMRasterBand band="3">
    <Histograms>
      <HistItem>
        <HistMin>-0.5</HistMin>
        <HistMax>1023.5</HistMax>
        <BucketCount>1024</BucketCount>
        <IncludeOutOfRange>1</IncludeOutOfRange>
        <Approximate>0</Approximate>
        <HistCounts>0|0|0|0|0|0|0|0|0|0|0|0|0|0|0|0|0|0|0|0|0|0|0|0|0|0|0|0|0|0|0|0|0|0|0|0|0|0|0|0|0|0|0|0|0|0|0|0|0|0|0|0|0|0|0|0|0|0|0|0|0|0|0|0|0|0|0|0|0|0|0|0|0|0|0|0|0|0|0|0|0|0|0|0|0|0|0|0|0|0|0|0|0|0|0|0|0|0|0|0|0|0|0|3|46|220|801|1463|2112|2491|2459|2723|2676|2701|2505|2014|1877|1595|1544|1490|1565|1647|1632|1583|1553|1652|2062|2612|3085|3407|3409|2517|1369|763|578|440|470|413|407|390|353|379|347|319|324|333|334|304|319|285|264|320|279|310|278|269|235|284|246|267|298|318|267|233|241|295|264|256|308|262|281|255|297|279|271|269|253|319|301|291|282|272|292|281|315|293|271|293|327|357|342|367|402|399|355|428|430|412|482|434|462|486|505|546|538|481|489|499|523|489|514|537|504|561|581|534|549|580|588|581|525|558|545|520|549|553|559|606|569|623|550|607|551|644|578|668|544|600|598|604|606|689|645|590|631|670|644|670|668|664|657|689|781|653|729|715|726|722|761|810|824|839|854|877|989|916|929|957|941|989|986|1110|1091|1055|1101|1115|1159|1186|1194|1186|1294|1217|1268|1361|1314|1339|1332|1464|1480|1580|1515|1557|1615|1537|1627|1585|1675|1616|1650|1674|1766|1700|1741|1738|1817|1863|1848|1953|1948|1967|2034|2046|2122|2231|2212|2075|2210|2254|2288|2271|2279|2389|2308|2274|2288|2433|2296|2355|2504|2428|2478|2515|2512|2482|2588|2616|2610|2676|2662|2753|2766|2716|2794|2709|2877|2893|2983|3042|3050|3162|3229|3305|3359|3445|3488|3621|3691|3823|3885|3986|4248|4426|4611|4745|4899|5133|5301|5306|5689|6130|6290|6330|6555|6743|7071|7085|7356|7289|7516|7799|8112|8332|8587|9027|8811|9343|9675|9518|10214|10936|11367|11763|12004|12430|12849|13218|13321|13225|13695|13914|13820|13854|13712|14015|13607|13516|13235|12806|12720|12468|12213|11796|11635|11223|10629|10381|10041|9502|9478|9401|9047|9039|8708|8631|8647|8481|8222|7776|8110|7853|7822|7705|7561|7460|7158|7191|6734|6767|6711|6709|6517|6734|6344|6530|6342|6269|6024|6062|6150|6204|5986|6038|6067|5824|5774|5866|5689|5732|5455|5407|5435|5324|5210|5404|5111|4990|4987|5050|4974|4940|4971|4746|4746|4800|4731|4699|4635|4674|4611|4562|4482|4583|4562|4576|4596|4525|4473|4452|4414|4492|4386|4397|4517|4412|4486|4396|4311|4323|4356|4626|4412|4583|4670|4729|4655|4646|4831|4836|4704|4876|5013|5086|5177|5197|5228|5306|5041|5063|5001|5053|5152|5049|5036|5010|5006|5004|5019|4863|4677|4801|4742|4714|4360|4503|4519|4468|4562|4487|4387|4442|4388|4565|4656|4413|4489|4469|4426|4481|4441|4504|4502|4672|4741|4840|4692|4864|4807|4829|4952|5086|5081|5278|5212|5470|5488|5289|5462|5521|5528|5442|5599|5726|5858|5895|5868|5978|6073|6252|6021|6249|6321|6489|6451|6623|6728|6850|6833|6844|6907|6950|7239|7140|7144|7107|7164|7205|7104|6893|7102|7030|7096|6968|6714|6818|6953|6658|6586|6344|6389|6227|6293|6126|6255|6037|5942|5863|5885|5580|5668|5661|5714|5486|5514|5445|5409|5366|5335|5235|5224|5172|5261|4936|5085|5094|4989|4798|4654|4868|4576|4643|4567|4517|4428|4535|4281|4295|4289|4098|4039|4028|4080|4125|3926|3860|3741|3720|3863|3585|3459|3460|3409|3267|3236|3166|3196|3039|3002|3013|2859|2894|2810|2704|2633|2712|2584|2500|2416|2420|2440|2433|2280|2262|2322|2264|2180|2247|2185|2068|2071|2044|2056|1982|2086|2015|1934|1968|1916|1772|1915|1778|1763|1762|1766|1791|1737|1626|1708|1575|1623|1571|1502|1484|1581|1532|1457|1494|1533|1448|1359|1383|1366|1376|1327|1314|1255|1257|1214|1166|1165|1206|1144|1133|1136|1053|1045|1078|992|972|921|876|918|878|835|890|885|847|789|824|771|800|792|733|799|654|646|648|599|570|596|552|516|474|482|484|439|437|412|413|359|388|343|370|311|318|324|336|325|279|293|293|310|270|272|268|246|225|232|248|236|247|225|174|204|210|178|202|183|224|214|184|183|180|182|158|189|195|182|140|195|140|154|144|147|149|136|157|154|144|130|152|127|114|137|150|107|120|104|119|95|114|105|121|104|107|101|104|106|98|86|95|121|99|78|76|90|85|102|68|62|80|80|88|54|75|82|68|69|66|70|69|55|72|58|65|66|63|50|45|65|44|56|43|46|42|58|40|41|51|54|50|36|43|40|41|51|21|47|35|35|28|36|32|29|32|31|37|18|38|21|28|34|28|33|27|22|27|17|26|36|22|29|17|28|28|28|22|20|15|29|21|20|23|18|10|22|16|19|31|24|22|22|10|14|12|15|11|19|11|21|11|11|15|11|11|14|16|13|19|12|14|10|12|8|16|18|7|9|13|19|16|4|11|13|11|10|10|14|12|5|13|6|11|15|8|14|6|10|4|11|10|12|9|13|10|15|8|7|9|2|10|5|9|14|5|10|7|13|7|13|5|9|7|9|12|21|7|9|13|10|10|8|15|15|12|8|20|23|18|29|22|33|34|69|486</HistCounts>
      </HistItem>
    </Histograms>
    <Metadata>
      <MDI key="RepresentationType">ATHEMATIC</MDI>
      <MDI key="STATISTICS_COVARIANCES">3959.429539735342,9309.004785173107,17883.2833323561,13828.62270948675</MDI>
      <MDI key="STATISTICS_MAXIMUM">1023</MDI>
      <MDI key="STATISTICS_MEAN">479.20144217766</MDI>
      <MDI key="STATISTICS_MINIMUM">103</MDI>
      <MDI key="STATISTICS_SKIPFACTORX">1</MDI>
      <MDI key="STATISTICS_SKIPFACTORY">1</MDI>
      <MDI key="STATISTICS_STDDEV">133.72839388984</MDI>
    </Metadata>
  </PAMRasterBand>
  <PAMRasterBand band="4">
    <Histograms>
      <HistItem>
        <HistMin>-0.5</HistMin>
        <HistMax>1023.5</HistMax>
        <BucketCount>1024</BucketCount>
        <IncludeOutOfRange>1</IncludeOutOfRange>
        <Approximate>0</Approximate>
        <HistCounts>0|0|0|0|0|0|0|0|0|0|0|0|0|0|0|0|0|0|0|0|0|0|0|0|0|0|0|0|0|0|0|0|0|0|0|0|0|0|0|0|0|0|0|0|0|0|0|0|0|0|0|0|0|0|0|0|0|0|0|0|0|0|0|0|150|2132|7222|10462|8615|6821|5118|4112|3396|2463|2097|1528|1141|918|750|684|594|553|508|524|481|434|438|408|364|432|375|412|359|414|390|376|364|397|364|385|428|338|359|390|410|357|374|341|361|333|339|355|323|327|319|295|310|331|324|316|316|333|331|348|313|306|327|334|292|332|329|313|359|362|353|388|368|399|417|354|404|420|368|359|381|367|365|364|404|370|395|425|414|444|401|451|419|401|472|448|431|391|428|391|400|401|424|412|460|425|377|379|404|423|384|440|387|385|402|456|405|381|387|416|404|428|486|452|448|442|459|493|488|477|527|563|476|544|533|563|598|526|610|621|595|668|690|658|704|704|719|759|916|871|885|915|913|912|946|957|852|913|942|931|996|1062|1055|1202|1339|1344|1448|1554|1647|1786|1877|1962|2221|2419|2495|2742|2862|2961|3375|3775|4225|4705|5448|5760|6221|6926|7433|8022|8921|9646|10682|11238|12200|12878|13514|13755|14228|14869|15219|15764|16154|16313|16589|16788|16894|17127|16910|16424|16004|15857|15498|14969|14056|13811|12622|11381|11094|10295|9544|8758|8057|7264|6941|6343|6029|5613|5221|5119|4822|4644|4494|4303|4050|3977|3741|3667|3692|3508|3550|3243|2945|2826|2784|2498|2333|2109|2065|1939|1866|1709|1653|1605|1505|1359|1331|1202|1241|1239|1222|1206|1171|1106|1161|1112|1113|1105|1213|1108|1066|1119|1124|1166|1097|1174|1079|1104|1147|1137|1188|1148|1261|1219|1192|1188|1251|1295|1242|1273|1332|1294|1307|1293|1281|1314|1369|1332|1346|1384|1378|1450|1390|1442|1455|1449|1408|1502|1494|1469|1514|1563|1544|1552|1546|1631|1590|1661|1626|1713|1705|1753|1825|1810|1867|1962|1979|1906|2125|1966|2136|2078|2185|2136|2226|2280|2373|2468|2461|2485|2580|2563|2647|2725|2704|2880|2847|2884|2995|2946|3068|3008|3205|3266|3451|3514|3593|3822|3810|3953|4013|4107|4228|4230|4288|4662|4418|4678|4466|4548|4758|4726|4671|4859|4705|4791|4751|4830|4857|4951|5022|5114|5053|5245|5190|5159|5527|5416|5471|5437|5485|5569|5562|5639|5846|5835|5994|6123|5893|6117|6170|6230|6235|6300|6558|6617|6678|6538|6664|6729|6823|6807|7135|7007|7127|7427|7337|7355|7441|7571|7516|7732|8098|8053|8163|8340|8412|8522|8530|8639|8637|8855|8939|8985|9268|9195|9256|9306|9183|9278|9239|9570|9370|9473|9749|9600|9666|10004|9823|9844|10060|10154|10347|10379|10053|10178|10189|9868|9824|9648|9735|9473|9410|9220|9264|9030|8885|8723|8553|8436|8654|8409|8297|8317|8200|7926|8099|7987|7859|7753|7469|7610|7582|7543|7448|7447|7361|7321|7338|7340|7324|7493|7191|7328|7161|7201|7347|7167|7029|6919|7065|6842|6772|6597|6594|6360|6261|6411|6111|6104|5973|6094|5876|5772|5929|5654|5565|5598|5471|5555|5384|5397|5257|5240|5210|5164|4972|5018|4878|5064|4913|4719|4734|4680|4700|4538|4387|4439|4402|4176|4142|4086|4124|3987|3952|3879|3789|3899|3717|3697|3648|3522|3487|3358|3350|3225|3278|3164|3203|3060|3019|2884|2688|2777|2650|2590|2642|2561|2561|2386|2443|2301|2238|2262|2033|2017|1966|1955|1804|1817|1748|1777|1628|1599|1627|1580|1603|1573|1461|1439|1341|1388|1256|1275|1269|1215|1270|1145|1127|1108|1064|1143|977|999|948|904|889|908|826|830|810|827|743|749|722|739|659|684|674|562|643|624|620|589|542|502|495|537|523|487|449|471|484|432|405|373|398|368|362|334|362|342|331|301|325|321|288|262|257|272|237|231|232|232|241|262|208|225|254|202|236|168|210|196|187|165|175|185|177|164|162|164|146|155|137|122|135|122|143|106|113|99|110|116|102|92|99|96|87|90|91|75|81|86|94|69|56|63|62|55|58|57|52|62|65|65|41|38|58|41|48|43|37|23|50|33|17|21|36|29|31|17|30|23|21|22|25|18|23|7|7|16|11|16|10|19|3|17|4|9|19|5|9|7|13|7|7|4|9|2|4|7|1|10|6|6|4|6|9|4|5|5|3|4|1|6|6|1|5|7|6|2|1|4|2|3|1|1|5|4|2|4|2|3|4|2|3|3|4|5|1|8|0|1|1|1|1|3|1|1|2|5|4|4|2|3|5|4|3|4|2|4|2|2|0|2|2|4|3|1|4|1|1|1|1|5|2|1|7|2|2|1|1|5|1|4|0|2|3|3|2|3|2|2|3|4|3|3|1|4|3|1|2|2|4|1|1|2|2|7|5|1|1|4|0|2|3|1|3|4|4|5|2|0|3|8|0|0|0|2|3|2|1|0|0|3|1|2|3|4|1|0|5|1|2|1|0|1|1|0|1|0|0|2|2|3|1|1|3|2|4|3|1|1|3|2|0|3|2|2|0|1|1|3|3|2|0|0|0|2|0|1|1|1|0|1|3|0|1|2|0|4|1|2|0|4|6|1|1|1|1|0|0|3|3|2|0|3|5|2|5|6</HistCounts>
      </HistItem>
    </Histograms>
    <Metadata>
      <MDI key="RepresentationType">ATHEMATIC</MDI>
      <MDI key="STATISTICS_COVARIANCES">-4430.962635072909,1411.599133658543,13828.62270948675,20707.58507430772</MDI>
      <MDI key="STATISTICS_MAXIMUM">1023</MDI>
      <MDI key="STATISTICS_MEAN">425.52950472473</MDI>
      <MDI key="STATISTICS_MINIMUM">64</MDI>
      <MDI key="STATISTICS_SKIPFACTORX">1</MDI>
      <MDI key="STATISTICS_SKIPFACTORY">1</MDI>
      <MDI key="STATISTICS_STDDEV">143.90130324048</MDI>
    </Metadata>
  </PAMRasterBand>
</PAMDataset>
